setup.py
blal/__init__.py
blal/_lal.so
blal/_lalframe.so
blal/_lalsimulation.so
blal/libFrame.so.1
blal/libfftw3.so.3
blal/libfftw3f.so.3
blal/libgsl.so.19
blal/libgslcblas.so.0
blal/libhdf5.so.10
blal/libhdf5_hl.so.10
blal/liblal.so.14
blal/liblalframe.so.10
blal/liblalsimulation.so.16
blal/liblalsupport.so.11
lal/__init__.py
lalframe/__init__.py
lalsimulation/__init__.py
pycbc_azure_binary_lal.egg-info/PKG-INFO
pycbc_azure_binary_lal.egg-info/SOURCES.txt
pycbc_azure_binary_lal.egg-info/dependency_links.txt
pycbc_azure_binary_lal.egg-info/requires.txt
pycbc_azure_binary_lal.egg-info/top_level.txt