Metadata-Version: 1.0
Name: pycbc-azure-binary-lal
Version: 0.0.6
Summary: some shared object files from lalsuite, no gaurantees
Home-page: UNKNOWN
Author: Alex Nitz
Author-email: alex.nitz@aei.mpg.de
License: UNKNOWN
Platform: UNKNOWN
